comp-0.4.6.data/data/share/man/man1/comp.1
comp-0.4.6.data/scripts/comp
comp-0.4.6.dist-info/DESCRIPTION.rst
comp-0.4.6.dist-info/METADATA
comp-0.4.6.dist-info/RECORD
comp-0.4.6.dist-info/WHEEL
comp-0.4.6.dist-info/metadata.json
comp-0.4.6.dist-info/top_level.txt
omp/__init__.py
omp/ie.py
omp/omp.py
omp/locale/vi/LC_MESSAGES/omp.mo
