Metadata-Version: 2.0
Name: comp
Version: 0.4.6
Summary: Curses Omni Media Player
Home-page: https://github.com/McSinyx/comp
Author: Nguyễn Gia Phong
Author-email: vn.mcsinyx@gmail.com
License: AGPLv3+
Keywords: youtube-dl mpv-wrapper curses console-application multimedia
Platform: POSIX
Classifier: Development Status :: 4 - Beta
Classifier: Environment :: Console :: Curses
Classifier: Intended Audience :: End Users/Desktop
Classifier: License :: OSI Approved :: GNU Affero General Public License v3
Classifier: Natural Language :: English
Classifier: Natural Language :: Vietnamese
Classifier: Operating System :: POSIX
Classifier: Programming Language :: Python :: 3.5
Classifier: Programming Language :: Python :: 3.6
Classifier: Topic :: Multimedia :: Sound/Audio :: Players
Classifier: Topic :: Multimedia :: Video :: Display
Requires-Python: >=3.5
Requires-Dist: python-mpv
Requires-Dist: youtube-dl
